sim_datasets/__init__.py
sim_datasets/__main__.py
sim_datasets/utils.py
sim_datasets/configs/bio_pop_growth.txt
sim_datasets/configs/blackbox.txt
sim_datasets/configs/chem_react.txt
sim_datasets/configs/feynman.txt
sim_datasets/configs/llm-srbench.bio_pop_growth.txt
sim_datasets/configs/llm-srbench.chem_react.txt
sim_datasets/configs/llm-srbench.lsrtransform.txt
sim_datasets/configs/llm-srbench.matsci.txt
sim_datasets/configs/llm-srbench.phys_osc.txt
sim_datasets/configs/llm-srbench.txt
sim_datasets/configs/lsrtransform.txt
sim_datasets/configs/matsci.txt
sim_datasets/configs/phys_osc.txt
sim_datasets/configs/srbench1.0.blackbox.txt
sim_datasets/configs/srbench1.0.feynman.txt
sim_datasets/configs/srbench1.0.strogatz.txt
sim_datasets/configs/srbench1.0.txt
sim_datasets/configs/srsd-feynman_easy.txt
sim_datasets/configs/srsd-feynman_easy_dummy.txt
sim_datasets/configs/srsd-feynman_hard.txt
sim_datasets/configs/srsd-feynman_hard_dummy.txt
sim_datasets/configs/srsd-feynman_medium.txt
sim_datasets/configs/srsd-feynman_medium_dummy.txt
sim_datasets/configs/srsd.srsd-feynman_easy.txt
sim_datasets/configs/srsd.srsd-feynman_easy_dummy.txt
sim_datasets/configs/srsd.srsd-feynman_hard.txt
sim_datasets/configs/srsd.srsd-feynman_hard_dummy.txt
sim_datasets/configs/srsd.srsd-feynman_medium.txt
sim_datasets/configs/srsd.srsd-feynman_medium_dummy.txt
sim_datasets/configs/srsd.txt
sim_datasets/configs/strogatz.txt
sim_datasets-0.1.1.dist-info/METADATA
sim_datasets-0.1.1.dist-info/WHEEL
sim_datasets-0.1.1.dist-info/entry_points.txt
sim_datasets-0.1.1.dist-info/RECORD
