Metadata-Version: 2.4
Name: sim-datasets
Version: 0.1.1
Summary: A unified platform solution for symbolic regression, providing comprehensive support for Scientific-Intelligent-Modeling toolkits. Seamlessly integrates with ModelScope and Hugging Face for efficient dataset access.
Project-URL: Homepage, https://github.com/scientific-intelligent-modelling/scientific-intelligent-modelling
Project-URL: Repository, https://github.com/scientific-intelligent-modelling/scientific-intelligent-modelling
Project-URL: Documentation, https://github.com/scientific-intelligent-modelling/scientific-intelligent-modelling
Project-URL: Issues, https://github.com/scientific-intelligent-modelling/scientific-intelligent-modelling/issues
Author-email: Ziwen Zhang <244824379@qq.com>, Kai Li <kai.li@ia.ac.cn>
Maintainer-email: Ziwen Zhang <244824379@qq.com>
License: GPL-3.0
Keywords: datasets,machine learning,scientific modeling,symbolic regression
Classifier: Development Status :: 3 - Alpha
Classifier: Intended Audience :: Developers
Classifier: Intended Audience :: Science/Research
Classifier: License :: OSI Approved :: GNU General Public License v3 (GPLv3)
Classifier: Operating System :: OS Independent
Classifier: Programming Language :: Python :: 3
Classifier: Programming Language :: Python :: 3.8
Classifier: Programming Language :: Python :: 3.9
Classifier: Programming Language :: Python :: 3.10
Classifier: Programming Language :: Python :: 3.11
Classifier: Programming Language :: Python :: 3.12
Classifier: Topic :: Scientific/Engineering :: Information Analysis
Classifier: Topic :: Software Development :: Libraries :: Python Modules
Requires-Python: >=3.8
Requires-Dist: requests>=2.25.0
